ssb_sparktools/__init__.py
ssb_sparktools/editing/__init__.py
ssb_sparktools/editing/controls.py
ssb_sparktools/editing/editing.py
ssb_sparktools/editing/micro_edditing.py
ssb_sparktools/logging/__init__.py
ssb_sparktools/logging/logging.py
ssb_sparktools/processing/__init__.py
ssb_sparktools/processing/processing.py
ssb_sparktools/quality/__init__.py
ssb_sparktools/quality/quality.py
ssb_sparktools/utils/__init__.py
ssb_sparktools/utils/utils.py
ssb_spark_tools-0.1.12.dist-info/METADATA
ssb_spark_tools-0.1.12.dist-info/WHEEL
ssb_spark_tools-0.1.12.dist-info/LICENSE
ssb_spark_tools-0.1.12.dist-info/RECORD
