Metadata-Version: 2.1
Name: ssb-spark-tools
Version: 0.1.12
Summary: A collection of data processing Spark functions for the use in Statistics Norway.
License: MIT
Author: Statistics Norway
Author-email: 81353974+arneso-ssb@users.noreply.github.com
Requires-Python: >=3.8,<3.12
Classifier: License :: OSI Approved :: MIT License
Classifier: Programming Language :: Python :: 3
Classifier: Programming Language :: Python :: 3.8
Classifier: Programming Language :: Python :: 3.9
Classifier: Programming Language :: Python :: 3.10
Classifier: Programming Language :: Python :: 3.11
Requires-Dist: numpy (>=1.20.3,<1.24)
Requires-Dist: pandas (>=1.5.1,<2.0.0)
Requires-Dist: pyspark (>=3.3.1,<3.4.0)
